additive/__init__.py
additive/additive.py
additive-0.6.0.dist-info/LICENSE
additive-0.6.0.dist-info/METADATA
additive-0.6.0.dist-info/WHEEL
additive-0.6.0.dist-info/top_level.txt
additive-0.6.0.dist-info/RECORD
